Workbook

Sheet Questions (2)
A1: 1. Calculate Total Sales for each order (Quantity × Unit_Price). | J1: 2
A2: 2. Calculate GST Amount using VLOOKUP from Product_Master. | J2: 2
A3: 3. Find Final Amount payable (Total Sales + GST). | J3: 2
A4: 4. Find Grand Total of Final Amount. | J4: 2
A5: 5. Count total number of orders using COUNTA. | J5: 2
A6: 6. Find Region-wise total sales using SUMIF. | J6: 2
A7: 7. Use IF to classify Quantity as High (>3) or Low (<=3). | J7: 2
A8: 8. Find the maximum and minimum Final Amount. | J8: 2
A9: 9. Extract month name from Sales_Date. | J9: 2
A10: 10. Sort Sales_Data by Final Amount (Descending). | J10: 2
A11: 11. Use INDEX-MATCH to fetch Product Category. | J11: 2
A12: 12. Calculate average marks of each student. | J12: 2
... A30: 30. Protect the Student_Marks sheet. | J30: 2
J32: =SUM(J1:J30) -> 60
F38: Answers
A42: Q1: | B42: 1. Calculate Total Sales for each order (Quantity × Unit_Price).
B44: Total sales
B45: {=Sales_Data!E2:E7*Sales_Data!F2:F7} -> 90000
B46: 75000
B47: 54000
B48: 45000
B49: 60000
B50: 90000
A52: Q2: | B52: Calculate GST Amount using VLOOKUP from Product_Master.
B54: Laptop | C54: =VLOOKUP(B54,Product_Master!A1:C4,3) -> 18
A56: Q3: | B56: Find Final Amount payable (Total Sales + GST).
B58: Final Amount : | C58: =SUM(_xlfn.ANCHORARRAY(B45)) -> 414000
A60: Product | B60: Price | C60: GST_%
A61: Laptop | B61: 45000 | C61: 18
A62: Mobile | B62: 15000 | C62: 12
A63: Tablet | C63: 12
A67: Q4: | B67: Find Grand Total of Final Amount.
A78: Q5: | B78: Count total number of orders using COUNTA.
B80: Total orders
B81: =COUNTA(Sales_Data!A2:A7) -> 6
A83: Q6: | B83: Find Region-wise total sales using SUMIF.
A92: Q7: | B92: 7. Use IF to classify Quantity as High (>3) or Low (<=3).

Sheet Product_Master
A1: Product | B1: Category | C1: GST_%
A2: Laptop | B2: Electronics | C2: 18
A3: Mobile | B3: Electronics | C3: 12
A4: Tablet | B4: Electronics | C4: 12

Sheet Sales_Data
A1: Order_ID | B1: Region | C1: Salesperson | D1: Product | E1: Quantity | F1: Unit_Price | G1: Sales_Date | H1: Total sales | I1: Final Total
A2: 301 | B2: North | C2: Amit | D2: Laptop | E2: 2 | F2: 45000 | G2: 05-01-2025 | H2: {=E2:E7*F2:F7} -> 90000
A3: 302 | B3: South | C3: Riya | D3: Mobile | E3: 5 | F3: 15000 | G3: 07-01-2025 | H3: 75000
A4: 303 | B4: East | C4: Kunal | D4: Tablet | E4: 3 | F4: 18000 | G4: 10-01-2025 | H4: 54000
A5: 304 | B5: West | C5: Neha | D5: Laptop | E5: 1 | F5: 45000 | G5: 12-01-2025 | H5: 45000
A6: 305 | B6: North | C6: Amit | D6: Mobile | E6: 4 | F6: 15000 | G6: 15-01-2025 | H6: 60000
A7: 306 | B7: South | C7: Riya | D7: Laptop | E7: 2 | F7: 45000 | G7: 18-01-2025 | H7: 90000

Sheet Questions
A1: 1. Calculate Total Sales for each order (Quantity × Unit_Price). | J1: 2
A2: 2. Calculate GST Amount using VLOOKUP from Product_Master. | J2: 2
A3: 3. Find Final Amount payable (Total Sales + GST). | J3: 2
A4: 4. Find Grand Total of Final Amount. | J4: 2
A5: 5. Count total number of orders using COUNTA. | J5: 2
A6: 6. Find Region-wise total sales using SUMIF. | J6: 2
A7: 7. Use IF to classify Quantity as High (>3) or Low (<=3). | J7: 2
A8: 8. Find the maximum and minimum Final Amount. | J8: 2
A9: 9. Extract month name from Sales_Date. | J9: 2
A10: 10. Sort Sales_Data by Final Amount (Descending). | J10: 2
A11: 11. Use INDEX-MATCH to fetch Product Category. | J11: 2
A12: 12. Calculate average marks of each student. | J12: 2
... A30: 30. Protect the Student_Marks sheet. | J30: 2
J32: =SUM(J1:J30) -> 60
F38: Answers
A42: Q1: | B42: 1. Calculate Total Sales for each order (Quantity × Unit_Price).
B44: Total sales
B45: {=Sales_Data!E2:E7*Sales_Data!F2:F7} -> 90000
B46: 75000
B47: 54000
B48: 45000
B49: 60000
B50: 90000
A52: Q2: | B52: Calculate GST Amount using VLOOKUP from Product_Master.
B54: Product | C54: Category | D54: GST_% | F54: Order_ID | G54: Region | H54: Salesperson | I54: Product | J54: Quantity | K54: Unit_Price | L54: Sales_Date | M54: Total sales | N54: With Gst | O54: GST Amount
B55: Laptop | C55: Electronics | D55: 18 | F55: 301 | G55: North | H55: Amit | I55: Laptop | J55: 2 | K55: 45000 | L55: 05-01-2025 | M55: {=J55:J60*K55:K60} -> 90000 | N55: =VLOOKUP(I55,B54:D57,3,0)/100 -> 0.18 | O55: =M55*N55 -> 16200
B56: Mobile | C56: Electronics | D56: 12 | F56: 302 | G56: South | H56: Riya | I56: Mobile | J56: 5 | K56: 15000 | L56: 07-01-2025 | M56: 75000 | N56: =VLOOKUP(I56,$B$54:$D$57,3,0)/100 -> 0.12 | O56: =M56*N56 -> 9000
B57: Tablet | C57: Electronics | D57: 12 | F57: 303 | G57: East | H57: Kunal | I57: Tablet | J57: 3 | K57: 18000 | L57: 10-01-2025 | M57: 54000 | N57: =VLOOKUP(I57,$B$54:$D$57,3,0)/100 -> 0.12 | O57: =M57*N57 -> 6480
F58: 304 | G58: West | H58: Neha | I58: Laptop | J58: 1 | K58: 45000 | L58: 12-01-2025 | M58: 45000 | N58: =VLOOKUP(I58,$B$54:$D$57,3,0)/100 -> 0.18 | O58: =M58*N58 -> 8100
F59: 305 | G59: North | H59: Amit | I59: Mobile | J59: 4 | K59: 15000 | L59: 15-01-2025 | M59: 60000 | N59: =VLOOKUP(I59,$B$54:$D$57,3,0)/100 -> 0.12 | O59: =M59*N59 -> 7200
F60: 306 | G60: South | H60: Riya | I60: Laptop | J60: 2 | K60: 45000 | L60: 18-01-2025 | M60: 90000 | N60: =VLOOKUP(I60,$B$54:$D$57,3,0)/100 -> 0.18 | O60: =M60*N60 -> 16200
A64: Q3: | B64: Find Final Amount payable (Total Sales + GST).
A66: Order_ID | B66: Region | C66: Salesperson | D66: Product | E66: Quantity | F66: Unit_Price | G66: Sales_Date | H66: Total sales | I66: With Gst | J66: GST Amount | K66: Final Payable Amount | O66: Product | P66: Category | Q66: GST_%
A67: 301 | B67: North | C67: Amit | D67: Laptop | E67: 2 | F67: 45000 | G67: 05-01-2025 | H67: {=E67:E72*F67:F72} -> 90000 | I67: =VLOOKUP(D67,$O$66:$Q$69,3,0)/100 -> 0.18 | J67: =H67*I67 -> 16200 | K67: =H67+J67 -> 106200 | O67: Laptop | P67: Electronics | Q67: 18
A68: 302 | B68: South | C68: Riya | D68: Mobile | E68: 5 | F68: 15000 | G68: 07-01-2025 | H68: 75000 | I68: =VLOOKUP(D68,$O$66:$Q$69,3,0)/100 -> 0.12 | J68: =H68*I68 -> 9000 | K68: =H68+J68 -> 84000 | O68: Mobile | P68: Electronics | Q68: 12
A69: 303 | B69: East | C69: Kunal | D69: Tablet | E69: 3 | F69: 18000 | G69: 10-01-2025 | H69: 54000 | I69: =VLOOKUP(D69,$O$66:$Q$69,3,0)/100 -> 0.12 | J69: =H69*I69 -> 6480 | K69: =H69+J69 -> 60480 | O69: Tablet | P69: Electronics | Q69: 12
A70: 304 | B70: West | C70: Neha | D70: Laptop | E70: 1 | F70: 45000 | G70: 12-01-2025 | H70: 45000 | I70: =VLOOKUP(D70,$O$66:$Q$69,3,0)/100 -> 0.18 | J70: =H70*I70 -> 8100 | K70: =H70+J70 -> 53100
A71: 305 | B71: North | C71: Amit | D71: Mobile | E71: 4 | F71: 15000 | G71: 15-01-2025 | H71: 60000 | I71: =VLOOKUP(D71,$O$66:$Q$69,3,0)/100 -> 0.12 | J71: =H71*I71 -> 7200 | K71: =H71+J71 -> 67200
A72: 306 | B72: South | C72: Riya | D72: Laptop | E72: 2 | F72: 45000 | G72: 18-01-2025 | H72: 90000 | I72: =VLOOKUP(D72,$O$66:$Q$69,3,0)/100 -> 0.18 | J72: =H72*I72 -> 16200 | K72: =H72+J72 -> 106200
A75: Q4: | B75: Find Grand Total of Final Amount.
A77: Order_ID | B77: Region | C77: Salesperson | D77: Product | E77: Quantity | F77: Unit_Price | G77: Sales_Date | H77: Total sales | I77: With Gst | J77: GST Amount | K77: Final Payable Amount
A78: 301 | B78: North | C78: Amit | D78: Laptop | E78: 2 | F78: 45000 | G78: 05-01-2025 | H78: {=E78:E83*F78:F83} -> 90000 | I78: =VLOOKUP(D78,$O$66:$Q$69,3,0)/100 -> 0.18 | J78: =H78*I78 -> 16200 | K78: =H78+J78 -> 106200
A79: 302 | B79: South | C79: Riya | D79: Mobile | E79: 5 | F79: 15000 | G79: 07-01-2025 | H79: 75000 | I79: =VLOOKUP(D79,$O$66:$Q$69,3,0)/100 -> 0.12 | J79: =H79*I79 -> 9000 | K79: =H79+J79 -> 84000
A80: 303 | B80: East | C80: Kunal | D80: Tablet | E80: 3 | F80: 18000 | G80: 10-01-2025 | H80: 54000 | I80: =VLOOKUP(D80,$O$66:$Q$69,3,0)/100 -> 0.12 | J80: =H80*I80 -> 6480 | K80: =H80+J80 -> 60480
A81: 304 | B81: West | C81: Neha | D81: Laptop | E81: 1 | F81: 45000 | G81: 12-01-2025 | H81: 45000 | I81: =VLOOKUP(D81,$O$66:$Q$69,3,0)/100 -> 0.18 | J81: =H81*I81 -> 8100 | K81: =H81+J81 -> 53100
A82: 305 | B82: North | C82: Amit | D82: Mobile | E82: 4 | F82: 15000 | G82: 15-01-2025 | H82: 60000 | I82: =VLOOKUP(D82,$O$66:$Q$69,3,0)/100 -> 0.12 | J82: =H82*I82 -> 7200 | K82: =H82+J82 -> 67200
A83: 306 | B83: South | C83: Riya | D83: Laptop | E83: 2 | F83: 45000 | G83: 18-01-2025 | H83: 90000 | I83: =VLOOKUP(D83,$O$66:$Q$69,3,0)/100 -> 0.18 | J83: =H83*I83 -> 16200 | K83: =H83+J83 -> 106200
J84: GRAND TOTAL | K84: =SUM(K78:K83) -> 477180
A86: Q5: | B86: Count total number of orders using COUNTA.
B88: Total orders
B89: =COUNTA(Sales_Data!A2:A7) -> 6
A91: Q6: | B91: Find Region-wise total sales using SUMIF.
B93: Region wise
A101: Q7: | B101: Use IF to classify Quantity as High (>3) or Low (<=3).
B103: Order_ID | C103: Region | D103: Salesperson | E103: Product | F103: Quantity | G103: Unit_Price | H103: Sales_Date | J103: IF > 3 | K103: IF<=3
B104: 301 | C104: North | D104: Amit | E104: Laptop | F104: 2 | G104: 45000 | H104: 05-01-2025 | J104: {=IF(F104:F109>3,"high","LOW")} -> #VALUE! | K104: {=IF(F104:F109<=3,"LOW","HIGH")} -> LOW
B105: 302 | C105: South | D105: Riya | E105: Mobile | F105: 5 | G105: 15000 | H105: 07-01-2025 | J105: {=IF(OR(F105:F110>=3,"HIGH"),"LOW")} -> LOW | K105: HIGH
B106: 303 | C106: East | D106: Kunal | E106: Tablet | F106: 3 | G106: 18000 | H106: 10-01-2025 | J106: {=IF(OR(F106:F111>=3,"HIGH"),"LOW")} -> LOW | K106: LOW
B107: 304 | C107: West | D107: Neha | E107: Laptop | F107: 1 | G107: 45000 | H107: 12-01-2025 | J107: {=IF(OR(F107:F112>=3,"HIGH"),"LOW")} -> LOW | K107: LOW
B108: 305 | C108: North | D108: Amit | E108: Mobile | F108: 4 | G108: 15000 | H108: 15-01-2025 | J108: {=IF(OR(F108:F113>=3,"HIGH"),"LOW")} -> LOW | K108: HIGH
B109: 306 | C109: South | D109: Riya | E109: Laptop | F109: 2 | G109: 45000 | H109: 18-01-2025 | J109: {=IF(OR(F109:F114>=3,"HIGH"),"LOW")} -> FALSE | K109: LOW
A112: Q8: | B112: Find the maximum and minimum Final Amount.
B114: Final Payable Amount | C114: MAX | D114: MIN
B115: =J67+H67 -> 106200 | C115: =MAX(B115:B120) -> 106200 | D115: =MIN(B115:B120) -> 53100
B116: =J68+H68 -> 84000
B117: =J69+H69 -> 60480
B118: =J70+H70 -> 53100
B119: =J71+H71 -> 67200
B120: =J72+H72 -> 106200
A123: Q9: | B123: Extract month name from Sales_Date.
B125: Sales_Date | C125: Months
B126: 05-01-2025 | C126: 45662
B127: 07-01-2025 | C127: 45663
B128: 10-01-2025 | C128: 45664
B129: 12-01-2025 | C129: 45665
B130: 15-01-2025 | C130: 45666
B131: 18-01-2025 | C131: 45667
A135: Q10:

Sheet Instructions
A1: MS Excel Practical Exam
A2: Total Questions: 30
A3: Difficulty Level: Medium
A4: Syllabus: Formulas, Logical Functions, Lookups, INDEX-MATCH, Pivot Tables & Charts, Data Analysis
A5: Attempt all questions using appropriate Excel tools/functions.

Sheet Student_Marks
A1: Student_ID | B1: Name | C1: Maths | D1: Statistics | E1: Excel | F1: Attendance_%
A2: 1 | B2: Rahul | C2: 78 | D2: 82 | E2: 85 | F2: 92
A3: 2 | B3: Sneha | C3: 88 | D3: 91 | E3: 90 | F3: 96
A4: 3 | B4: Arjun | C4: 65 | D4: 70 | E4: 72 | F4: 85
A5: 4 | B5: Pooja | C5: 92 | D5: 89 | E5: 94 | F5: 98
A6: 5 | B6: Vikas | C6: 55 | D6: 60 | E6: 58 | F6: 80
